quantvn/__init__.py
quantvn/crypto/__init__.py
quantvn/crypto/data/__init__.py
quantvn/crypto/data/derivatives.py
quantvn/crypto/data/download.py
quantvn/crypto/metrics/__init__.py
quantvn/crypto/metrics/backtest.py
quantvn/crypto/metrics/metrics.py
quantvn/metrics/__init__.py
quantvn/metrics/portfolio.py
quantvn/metrics/single_asset.py
quantvn/metrics/st.py
quantvn/paper/__init__.py
quantvn/paper/portfolio.py
quantvn/paper/single_asset.py
quantvn/vn/__init__.py
quantvn/vn/data/__init__.py
quantvn/vn/data/const.py
quantvn/vn/data/core.py
quantvn/vn/data/derivatives.py
quantvn/vn/data/stocks.py
quantvn/vn/data/utils.py
quantvn/vn/metrics/__init__.py
quantvn/vn/metrics/backtest.py
quantvn/vn/metrics/metrics.py
quantvn-0.1.7.dist-info/licenses/LICENSE
quantvn-0.1.7.dist-info/METADATA
quantvn-0.1.7.dist-info/WHEEL
quantvn-0.1.7.dist-info/top_level.txt
quantvn-0.1.7.dist-info/RECORD
